{
  "concepts": [
    {
      "black_list": false,
      "code": "58151-2",
      "code_system": "2.16.840.1.113883.6.1",
      "code_system_name": "LOINC",
      "code_system_version": null,
      "display_name": "Prior assessment Brief Interview for Mental Status (BIMS) summary score MDSv3",
      "white_list": false
    },
    {
      "black_list": false,
      "code": "71492-3",
      "code_system": "2.16.840.1.113883.6.1",
      "code_system_name": "LOINC",
      "code_system_version": null,
      "display_name": "Total score SLUMS",
      "white_list": false
    },
    {
      "black_list": false,
      "code": "71493-1",
      "code_system": "2.16.840.1.113883.6.1",
      "code_system_name": "LOINC",
      "code_system_version": null,
      "display_name": "Total score IQCODE",
      "white_list": false
    },
    {
      "black_list": false,
      "code": "71722-3",
      "code_system": "2.16.840.1.113883.6.1",
      "code_system_name": "LOINC",
      "code_system_version": null,
      "display_name": "Total score AD8",
      "white_list": false
    },
    {
      "black_list": false,
      "code": "72106-8",
      "code_system": "2.16.840.1.113883.6.1",
      "code_system_name": "LOINC",
      "code_system_version": null,
      "display_name": "Total score MMSE",
      "white_list": false
    },
    {
      "black_list": false,
      "code": "72172-0",
      "code_system": "2.16.840.1.113883.6.1",
      "code_system_name": "LOINC",
      "code_system_version": null,
      "display_name": "Total Score MoCA",
      "white_list": false
    },
    {
      "black_list": false,
      "code": "72173-8",
      "code_system": "2.16.840.1.113883.6.1",
      "code_system_name": "LOINC",
      "code_system_version": null,
      "display_name": "Total Score BOMC",
      "white_list": false
    }
  ],
  "display_name": "Standardized Tools for Assessment of Cognition",
  "oid": "2.16.840.1.113883.3.526.3.1006",
  "version": "20121025"
}