{
  "concepts": [
    {
      "black_list": false,
      "code": "24467-3",
      "code_system": "2.16.840.1.113883.6.1",
      "code_system_name": "LOINC",
      "code_system_version": null,
      "display_name": "CD3+CD4+ (T4 helper) cells [#/volume] in Blood",
      "white_list": false
    },
    {
      "black_list": false,
      "code": "32515-9",
      "code_system": "2.16.840.1.113883.6.1",
      "code_system_name": "LOINC",
      "code_system_version": null,
      "display_name": "CD3+CD4+ (T4 helper) cells [#/volume] in Unspecified specimen",
      "white_list": false
    },
    {
      "black_list": false,
      "code": "32532-4",
      "code_system": "2.16.840.1.113883.6.1",
      "code_system_name": "LOINC",
      "code_system_version": null,
      "display_name": "CD3+CD4+ (T4 helper) cells [#/volume] in Bone marrow",
      "white_list": false
    },
    {
      "black_list": false,
      "code": "40898-9",
      "code_system": "2.16.840.1.113883.6.1",
      "code_system_name": "LOINC",
      "code_system_version": null,
      "display_name": "CD3+CD4+ (T4 helper) cells [#/volume] in Tissue",
      "white_list": false
    },
    {
      "black_list": false,
      "code": "63450-1",
      "code_system": "2.16.840.1.113883.6.1",
      "code_system_name": "LOINC",
      "code_system_version": null,
      "display_name": "CD3+CD4+ (T4 helper) cells [#/volume] in Cerebral spinal fluid",
      "white_list": false
    }
  ],
  "display_name": "CD4+ Count",
  "oid": "2.16.840.1.113883.3.464.1003.121.12.1004",
  "version": "20121025"
}