{
  "concepts": [
    {
      "black_list": false,
      "code": "121868005",
      "code_system": "2.16.840.1.113883.6.96",
      "code_system_name": "SNOMED-CT",
      "code_system_version": null,
      "display_name": "Total cholesterol measurement (procedure)",
      "white_list": false
    },
    {
      "black_list": false,
      "code": "14647-2",
      "code_system": "2.16.840.1.113883.6.1",
      "code_system_name": "LOINC",
      "code_system_version": null,
      "display_name": "Cholesterol [Moles/volume] in Serum or Plasma",
      "white_list": false
    },
    {
      "black_list": false,
      "code": "2093-3",
      "code_system": "2.16.840.1.113883.6.1",
      "code_system_name": "LOINC",
      "code_system_version": null,
      "display_name": "Cholesterol [Mass/volume] in Serum or Plasma",
      "white_list": false
    },
    {
      "black_list": false,
      "code": "270996006",
      "code_system": "2.16.840.1.113883.6.96",
      "code_system_name": "SNOMED-CT",
      "code_system_version": null,
      "display_name": "Serum cholesterol measurement (procedure)",
      "white_list": false
    },
    {
      "black_list": false,
      "code": "412808005",
      "code_system": "2.16.840.1.113883.6.96",
      "code_system_name": "SNOMED-CT",
      "code_system_version": null,
      "display_name": "Serum total cholesterol measurement (procedure)",
      "white_list": false
    },
    {
      "black_list": false,
      "code": "77068002",
      "code_system": "2.16.840.1.113883.6.96",
      "code_system_name": "SNOMED-CT",
      "code_system_version": null,
      "display_name": "Cholesterol measurement (procedure)",
      "white_list": false
    },
    {
      "black_list": false,
      "code": "82465",
      "code_system": "2.16.840.1.113883.6.12",
      "code_system_name": "CPT",
      "code_system_version": null,
      "display_name": "Cholesterol, serum or whole blood, total",
      "white_list": false
    }
  ],
  "display_name": "Total Cholesterol",
  "oid": "2.16.840.1.113883.3.600.879",
  "version": "20121025"
}